{"object_name": "aggregate", "timestamps": [{"timestamp": 1653890401000, "instances": [{"instance_keys": "aggr0", "key_counters": "instance_name", "counters": [{"counter_name": "instance_name", "value": "aggr0"}, {"counter_name": "total_transfers", "value": "1128775254"}, {"counter_name": "user_reads", "value": "814635818"}, {"counter_name": "user_writes", "value": "195476069"}, {"counter_name": "cp_reads", "value": "118663367"}, {"counter_name": "user_read_blocks", "value": "19623388778"}, {"counter_name": "user_write_blocks", "value": "2909242630"}, {"counter_name": "cp_read_blocks", "value": "807995547"}]}]}]}
{"object_name": "aggregate", "timestamps": [{"timestamp": 1653894000000, "instances": [{"instance_keys": "aggr0", "key_counters": "instance_name", "counters": [{"counter_name": "instance_name", "value": "aggr0"}, {"counter_name": "total_transfers", "value": "1128807826"}, {"counter_name": "user_reads", "value": "814638526"}, {"counter_name": "user_writes", "value": "195494839"}, {"counter_name": "cp_reads", "value": "118674461"}, {"counter_name": "user_read_blocks", "value": "19623392581"}, {"counter_name": "user_write_blocks", "value": "2909431077"}, {"counter_name": "cp_read_blocks", "value": "808067422"}]}]}]}
{"object_name": "aggregate", "timestamps": [{"timestamp": 1653897600000, "instances": [{"instance_keys": "aggr0", "key_counters": "instance_name", "counters": [{"counter_name": "instance_name", "value": "aggr0"}, {"counter_name": "total_transfers", "value": "1128838815"}, {"counter_name": "user_reads", "value": "814641169"}, {"counter_name": "user_writes", "value": "195513133"}, {"counter_name": "cp_reads", "value": "118684513"}, {"counter_name": "user_read_blocks", "value": "19623396329"}, {"counter_name": "user_write_blocks", "value": "2909605417"}, {"counter_name": "cp_read_blocks", "value": "808136282"}]}]}]}
{"object_name": "aggregate", "timestamps": [{"timestamp": 1653901200000, "instances": [{"instance_keys": "aggr0", "key_counters": "instance_name", "counters": [{"counter_name": "instance_name", "value": "aggr0"}, {"counter_name": "total_transfers", "value": "1128871815"}, {"counter_name": "user_reads", "value": "814644046"}, {"counter_name": "user_writes", "value": "195532123"}, {"counter_name": "cp_reads", "value": "118695646"}, {"counter_name": "user_read_blocks", "value": "19623400296"}, {"counter_name": "user_write_blocks", "value": "2909778116"}, {"counter_name": "cp_read_blocks", "value": "808204174"}]}]}]}
{"object_name": "aggregate", "timestamps": [{"timestamp": 1653904800000, "instances": [{"instance_keys": "aggr0", "key_counters": "instance_name", "counters": [{"counter_name": "instance_name", "value": "aggr0"}, {"counter_name": "total_transfers", "value": "1128901471"}, {"counter_name": "user_reads", "value": "814646850"}, {"counter_name": "user_writes", "value": "195549675"}, {"counter_name": "cp_reads", "value": "118704946"}, {"counter_name": "user_read_blocks", "value": "19623404190"}, {"counter_name": "user_write_blocks", "value": "2909951339"}, {"counter_name": "cp_read_blocks", "value": "808271650"}]}]}]}
{"object_name": "aggregate", "timestamps": [{"timestamp": 1653908400000, "instances": [{"instance_keys": "aggr0", "key_counters": "instance_name", "counters": [{"counter_name": "instance_name", "value": "aggr0"}, {"counter_name": "total_transfers", "value": "1128932958"}, {"counter_name": "user_reads", "value": "814649578"}, {"counter_name": "user_writes", "value": "195567939"}, {"counter_name": "cp_reads", "value": "118715441"}, {"counter_name": "user_read_blocks", "value": "19623408013"}, {"counter_name": "user_write_blocks", "value": "2910122985"}, {"counter_name": "cp_read_blocks", "value": "808340596"}]}]}]}
{"object_name": "aggregate", "timestamps": [{"timestamp": 1653912000000, "instances": [{"instance_keys": "aggr0", "key_counters": "instance_name", "counters": [{"counter_name": "instance_name", "value": "aggr0"}, {"counter_name": "total_transfers", "value": "1128965331"}, {"counter_name": "user_reads", "value": "814652251"}, {"counter_name": "user_writes", "value": "195586878"}, {"counter_name": "cp_reads", "value": "118726202"}, {"counter_name": "user_read_blocks", "value": "19623411781"}, {"counter_name": "user_write_blocks", "value": "2910295872"}, {"counter_name": "cp_read_blocks", "value": "808410574"}]}]}]}
{"object_name": "aggregate", "timestamps": [{"timestamp": 1653915600000, "instances": [{"instance_keys": "aggr0", "key_counters": "instance_name", "counters": [{"counter_name": "instance_name", "value": "aggr0"}, {"counter_name": "total_transfers", "value": "1128996552"}, {"counter_name": "user_reads", "value": "814655149"}, {"counter_name": "user_writes", "value": "195605049"}, {"counter_name": "cp_reads", "value": "118736354"}, {"counter_name": "user_read_blocks", "value": "19623415769"}, {"counter_name": "user_write_blocks", "value": "2910467360"}, {"counter_name": "cp_read_blocks", "value": "808479467"}]}]}]}
{"object_name": "aggregate", "timestamps": [{"timestamp": 1653919200000, "instances": [{"instance_keys": "aggr0", "key_counters": "instance_name", "counters": [{"counter_name": "instance_name", "value": "aggr0"}, {"counter_name": "total_transfers", "value": "1129027707"}, {"counter_name": "user_reads", "value": "814658163"}, {"counter_name": "user_writes", "value": "195623092"}, {"counter_name": "cp_reads", "value": "118746452"}, {"counter_name": "user_read_blocks", "value": "19623422098"}, {"counter_name": "user_write_blocks", "value": "2910652929"}, {"counter_name": "cp_read_blocks", "value": "808551637"}]}]}]}
{"object_name": "aggregate", "timestamps": [{"timestamp": 1653922800000, "instances": [{"instance_keys": "aggr0", "key_counters": "instance_name", "counters": [{"counter_name": "instance_name", "value": "aggr0"}, {"counter_name": "total_transfers", "value": "1129054807"}, {"counter_name": "user_reads", "value": "814660893"}, {"counter_name": "user_writes", "value": "195639377"}, {"counter_name": "cp_reads", "value": "118754537"}, {"counter_name": "user_read_blocks", "value": "19623426086"}, {"counter_name": "user_write_blocks", "value": "2910815086"}, {"counter_name": "cp_read_blocks", "value": "808607614"}]}]}]}
{"object_name": "aggregate", "timestamps": [{"timestamp": 1653926400000, "instances": [{"instance_keys": "aggr0", "key_counters": "instance_name", "counters": [{"counter_name": "instance_name", "value": "aggr0"}, {"counter_name": "total_transfers", "value": "1129084755"}, {"counter_name": "user_reads", "value": "814663616"}, {"counter_name": "user_writes", "value": "195656882"}, {"counter_name": "cp_reads", "value": "118764257"}, {"counter_name": "user_read_blocks", "value": "19623429967"}, {"counter_name": "user_write_blocks", "value": "2910980832"}, {"counter_name": "cp_read_blocks", "value": "808673093"}]}]}]}
{"object_name": "aggregate", "timestamps": [{"timestamp": 1653930000000, "instances": [{"instance_keys": "aggr0", "key_counters": "instance_name", "counters": [{"counter_name": "instance_name", "value": "aggr0"}, {"counter_name": "total_transfers", "value": "1129114432"}, {"counter_name": "user_reads", "value": "814666329"}, {"counter_name": "user_writes", "value": "195674336"}, {"counter_name": "cp_reads", "value": "118773767"}, {"counter_name": "user_read_blocks", "value": "19623433770"}, {"counter_name": "user_write_blocks", "value": "2911150034"}, {"counter_name": "cp_read_blocks", "value": "808738752"}]}]}]}
{"object_name": "aggregate", "timestamps": [{"timestamp": 1653933600000, "instances": [{"instance_keys": "aggr0", "key_counters": "instance_name", "counters": [{"counter_name": "instance_name", "value": "aggr0"}, {"counter_name": "total_transfers", "value": "1129147902"}, {"counter_name": "user_reads", "value": "814669004"}, {"counter_name": "user_writes", "value": "195693804"}, {"counter_name": "cp_reads", "value": "118785094"}, {"counter_name": "user_read_blocks", "value": "19623437535"}, {"counter_name": "user_write_blocks", "value": "2911338568"}, {"counter_name": "cp_read_blocks", "value": "808814015"}]}]}]}
{"object_name": "aggregate", "timestamps": [{"timestamp": 1653937200000, "instances": [{"instance_keys": "aggr0", "key_counters": "instance_name", "counters": [{"counter_name": "instance_name", "value": "aggr0"}, {"counter_name": "total_transfers", "value": "1129178939"}, {"counter_name": "user_reads", "value": "814671634"}, {"counter_name": "user_writes", "value": "195711957"}, {"counter_name": "cp_reads", "value": "118795348"}, {"counter_name": "user_read_blocks", "value": "19623441260"}, {"counter_name": "user_write_blocks", "value": "2911509911"}, {"counter_name": "cp_read_blocks", "value": "808878169"}]}]}]}
{"object_name": "aggregate", "timestamps": [{"timestamp": 1653940800000, "instances": [{"instance_keys": "aggr0", "key_counters": "instance_name", "counters": [{"counter_name": "instance_name", "value": "aggr0"}, {"counter_name": "total_transfers", "value": "1129208958"}, {"counter_name": "user_reads", "value": "814674415"}, {"counter_name": "user_writes", "value": "195729723"}, {"counter_name": "cp_reads", "value": "118804820"}, {"counter_name": "user_read_blocks", "value": "19623445146"}, {"counter_name": "user_write_blocks", "value": "2911684013"}, {"counter_name": "cp_read_blocks", "value": "808940796"}]}]}]}
{"object_name": "aggregate", "timestamps": [{"timestamp": 1653944400000, "instances": [{"instance_keys": "aggr0", "key_counters": "instance_name", "counters": [{"counter_name": "instance_name", "value": "aggr0"}, {"counter_name": "total_transfers", "value": "1129240089"}, {"counter_name": "user_reads", "value": "814677061"}, {"counter_name": "user_writes", "value": "195748122"}, {"counter_name": "cp_reads", "value": "118814906"}, {"counter_name": "user_read_blocks", "value": "19623448927"}, {"counter_name": "user_write_blocks", "value": "2911857515"}, {"counter_name": "cp_read_blocks", "value": "809010577"}]}]}]}
{"object_name": "aggregate", "timestamps": [{"timestamp": 1653948000000, "instances": [{"instance_keys": "aggr0", "key_counters": "instance_name", "counters": [{"counter_name": "instance_name", "value": "aggr0"}, {"counter_name": "total_transfers", "value": "1129272416"}, {"counter_name": "user_reads", "value": "814679845"}, {"counter_name": "user_writes", "value": "195766830"}, {"counter_name": "cp_reads", "value": "118825741"}, {"counter_name": "user_read_blocks", "value": "19623452801"}, {"counter_name": "user_write_blocks", "value": "2912043629"}, {"counter_name": "cp_read_blocks", "value": "809081233"}]}]}]}
{"object_name": "aggregate", "timestamps": [{"timestamp": 1653951600000, "instances": [{"instance_keys": "aggr0", "key_counters": "instance_name", "counters": [{"counter_name": "instance_name", "value": "aggr0"}, {"counter_name": "total_transfers", "value": "1129304682"}, {"counter_name": "user_reads", "value": "814682461"}, {"counter_name": "user_writes", "value": "195785574"}, {"counter_name": "cp_reads", "value": "118836647"}, {"counter_name": "user_read_blocks", "value": "19623456517"}, {"counter_name": "user_write_blocks", "value": "2912214925"}, {"counter_name": "cp_read_blocks", "value": "809146499"}]}]}]}
{"object_name": "aggregate", "timestamps": [{"timestamp": 1653955200000, "instances": [{"instance_keys": "aggr0", "key_counters": "instance_name", "counters": [{"counter_name": "instance_name", "value": "aggr0"}, {"counter_name": "total_transfers", "value": "1129335862"}, {"counter_name": "user_reads", "value": "814685095"}, {"counter_name": "user_writes", "value": "195803777"}, {"counter_name": "cp_reads", "value": "118846990"}, {"counter_name": "user_read_blocks", "value": "19623460246"}, {"counter_name": "user_write_blocks", "value": "2912387818"}, {"counter_name": "cp_read_blocks", "value": "809214338"}]}]}]}
{"object_name": "aggregate", "timestamps": [{"timestamp": 1653958800000, "instances": [{"instance_keys": "aggr0", "key_counters": "instance_name", "counters": [{"counter_name": "instance_name", "value": "aggr0"}, {"counter_name": "total_transfers", "value": "1129368094"}, {"counter_name": "user_reads", "value": "814687785"}, {"counter_name": "user_writes", "value": "195822596"}, {"counter_name": "cp_reads", "value": "118857713"}, {"counter_name": "user_read_blocks", "value": "19623464231"}, {"counter_name": "user_write_blocks", "value": "2912566000"}, {"counter_name": "cp_read_blocks", "value": "809283855"}]}]}]}
{"object_name": "aggregate", "timestamps": [{"timestamp": 1653962400000, "instances": [{"instance_keys": "aggr0", "key_counters": "instance_name", "counters": [{"counter_name": "instance_name", "value": "aggr0"}, {"counter_name": "total_transfers", "value": "1129400879"}, {"counter_name": "user_reads", "value": "814690453"}, {"counter_name": "user_writes", "value": "195841645"}, {"counter_name": "cp_reads", "value": "118868781"}, {"counter_name": "user_read_blocks", "value": "19623467989"}, {"counter_name": "user_write_blocks", "value": "2912758298"}, {"counter_name": "cp_read_blocks", "value": "809360032"}]}]}]}
{"object_name": "aggregate", "timestamps": [{"timestamp": 1653966000000, "instances": [{"instance_keys": "aggr0", "key_counters": "instance_name", "counters": [{"counter_name": "instance_name", "value": "aggr0"}, {"counter_name": "total_transfers", "value": "1129431926"}, {"counter_name": "user_reads", "value": "814693180"}, {"counter_name": "user_writes", "value": "195859842"}, {"counter_name": "cp_reads", "value": "118878904"}, {"counter_name": "user_read_blocks", "value": "19623471811"}, {"counter_name": "user_write_blocks", "value": "2912932278"}, {"counter_name": "cp_read_blocks", "value": "809431089"}]}]}]}
{"object_name": "aggregate", "timestamps": [{"timestamp": 1653969600000, "instances": [{"instance_keys": "aggr0", "key_counters": "instance_name", "counters": [{"counter_name": "instance_name", "value": "aggr0"}, {"counter_name": "total_transfers", "value": "1129465598"}, {"counter_name": "user_reads", "value": "814695939"}, {"counter_name": "user_writes", "value": "195879355"}, {"counter_name": "cp_reads", "value": "118890304"}, {"counter_name": "user_read_blocks", "value": "19623475665"}, {"counter_name": "user_write_blocks", "value": "2913109826"}, {"counter_name": "cp_read_blocks", "value": "809505542"}]}]}]}
{"object_name": "aggregate", "timestamps": [{"timestamp": 1653973200000, "instances": [{"instance_keys": "aggr0", "key_counters": "instance_name", "counters": [{"counter_name": "instance_name", "value": "aggr0"}, {"counter_name": "total_transfers", "value": "1129789143"}, {"counter_name": "user_reads", "value": "814971780"}, {"counter_name": "user_writes", "value": "195907572"}, {"counter_name": "cp_reads", "value": "118909791"}, {"counter_name": "user_read_blocks", "value": "19623766085"}, {"counter_name": "user_write_blocks", "value": "2913556609"}, {"counter_name": "cp_read_blocks", "value": "809628282"}]}]}]}
